monostate/__init__.py
monostate/monostate.py
monostate-0.0.12.dist-info/LICENSE
monostate-0.0.12.dist-info/WHEEL
monostate-0.0.12.dist-info/METADATA
monostate-0.0.12.dist-info/RECORD
