Metadata-Version: 2.1
Name: monostate
Version: 0.0.12
Summary: Dependency-free monostate owner base class
Home-page: https://github.com/w2sv/monostate
License: MIT
Keywords: singleton,borg,design-patterns,anti-patterns
Author: w2sv
Author-email: zangenbergjanek@googlemail.com
Requires-Python: >=3.6,<4.0
Classifier: License :: OSI Approved :: MIT License
Classifier: Operating System :: OS Independent
Classifier: Programming Language :: Python :: 3
Classifier: Programming Language :: Python :: 3.10
Classifier: Programming Language :: Python :: 3.6
Classifier: Programming Language :: Python :: 3.7
Classifier: Programming Language :: Python :: 3.8
Classifier: Programming Language :: Python :: 3.9
Project-URL: Repository, https://github.com/w2sv/monostate
